dvd/__init__.py
dvd/ifo/__init__.py
dvd/ifo/util.py
dvd/ifo/vts.py
dvd/main.py
dvd/scripts/extract_titles.py
dvdutils-0.1.0.dist-info/METADATA
dvdutils-0.1.0.dist-info/WHEEL
dvdutils-0.1.0.dist-info/entry_points.txt
dvdutils-0.1.0.dist-info/RECORD
