Metadata-Version: 2.1
Name: dvdutils
Version: 0.1.0
Summary: DVD IFO parser and title extracter.
Author-Email: Julia Rose <papercrane@reversefold.com>
License: MIT
Requires-Python: >=3.12
Requires-Dist: attrs>=25.3.0
Requires-Dist: docopt-ng>=0.9.0
Requires-Dist: more-itertools>=10.7.0
Requires-Dist: cattrs>=25.1.1
Provides-Extra: dev
Requires-Dist: jupyter>=1.1.1; extra == "dev"
Requires-Dist: ipython>=9.4.0; extra == "dev"
Requires-Dist: ipdb>=0.13.13; extra == "dev"
